{"skeleton":{"hash":"QFJv04QmWWQ","spine":"4.1.23","x":-11.46,"y":-0.05,"width":24.43,"height":51.28,"images":"","audio":""},"bones":[{"name":"root","y":0.08},{"name":"Torso bone","parent":"root","length":188.5,"rotation":90.49,"x":-0.03,"y":15.74,"scaleX":0.1122,"scaleY":0.1122},{"name":"Head bone","parent":"Torso bone","length":126.91,"rotation":-0.97,"x":188.5},{"name":"Right arm bone top","parent":"Torso bone","length":81.84,"rotation":-167.63,"x":174.66,"y":-53.43},{"name":"Right arm bone bottom","parent":"Right arm bone top","length":72.66,"rotation":12.22,"x":82.36,"y":-0.12},{"name":"Left arm bone top","parent":"Torso bone","length":86.88,"rotation":165.18,"x":177.72,"y":55.25},{"name":"Left arm bone bottom","parent":"Left arm bone top","length":78.19,"rotation":20.45,"x":86.88,"scaleX":1.0083,"scaleY":1.0083},{"name":"Left leg top","parent":"root","length":8.02,"rotation":-77.19,"x":-4.98,"y":16.52},{"name":"Right leg top","parent":"root","length":8.25,"rotation":-77.77,"x":3.82,"y":16.65},{"name":"Right leg bottom","parent":"Right leg top","length":8.74,"rotation":-17.96,"x":8.15,"y":0.02},{"name":"Left leg bottom","parent":"Left leg top","length":8.84,"rotation":-18.48,"x":7.98,"y":-0.06}],"slots":[{"name":"Arm_top","bone":"Right arm bone top","attachment":"Arm_top"},{"name":"Arm_bottom","bone":"Right arm bone bottom","attachment":"Arm_bottom"},{"name":"Leg top","bone":"Right leg top","attachment":"Leg top"},{"name":"Leg bottom","bone":"Right leg bottom","attachment":"Leg bottom"},{"name":"Leg top2","bone":"Left leg top","attachment":"Leg top"},{"name":"Leg bottom2","bone":"Left leg bottom","attachment":"Leg bottom"},{"name":"Torso","bone":"Torso bone","attachment":"Torso"},{"name":"Head","bone":"Head bone","attachment":"Head"},{"name":"Arm_top2","bone":"Left arm bone top","attachment":"Arm_top"},{"name":"Arm_bottom2","bone":"Left arm bone bottom","attachment":"Arm_bottom"}],"skins":[{"name":"default","attachments":{"Arm_bottom":{"Arm_bottom":{"x":29.47,"y":-3.11,"rotation":90.75,"width":35,"height":93}},"Arm_bottom2":{"6af34888-93e4-4ce6-8f04-3758bbca36f4":{"x":144.18,"y":17.31,"scaleX":5.9472,"scaleY":5.9472,"width":48,"height":14},"Arm_bottom":{"x":33.09,"y":-1.04,"rotation":89.22,"width":35,"height":93}},"Arm_top":{"Arm_top":{"x":43.41,"y":-2.69,"rotation":107.48,"width":56,"height":101}},"Arm_top2":{"Arm_top":{"x":50.2,"y":-0.31,"rotation":109.44,"width":56,"height":101}},"Head":{"Head":{"x":61.11,"y":-1.25,"rotation":-89.52,"width":116,"height":132}},"Leg bottom":{"Leg bottom":{"x":3.44,"y":-0.03,"scaleX":0.1122,"scaleY":0.1122,"rotation":95.73,"width":48,"height":96}},"Leg bottom2":{"Leg bottom":{"x":3.48,"y":0.06,"scaleX":0.1122,"scaleY":0.1122,"rotation":95.67,"width":48,"height":96}},"Leg top":{"Leg top":{"x":4.57,"y":0.05,"scaleX":0.1122,"scaleY":0.1122,"rotation":77.77,"width":52,"height":87}},"Leg top2":{"Leg top":{"x":4.46,"y":0.14,"scaleX":0.1122,"scaleY":0.1122,"rotation":77.19,"width":52,"height":87}},"Torso":{"Torso":{"x":94.37,"y":1.77,"rotation":-90.49,"width":125,"height":190}}}}],"animations":{"Aim":{"slots":{"Arm_bottom2":{"attachment":[{"name":"6af34888-93e4-4ce6-8f04-3758bbca36f4"}]}},"bones":{"Left arm bone top":{"rotate":[{"value":74.38}]},"Right arm bone top":{"rotate":[{},{"time":0.3333,"value":-4.37},{"time":0.6667}]},"Left arm bone bottom":{"rotate":[{"value":10.48}]}}},"animation":{},"Crouch":{"bones":{"Head bone":{"rotate":[{},{"time":0.3333,"value":-6.4},{"time":0.6667}]},"Torso bone":{"rotate":[{"value":-6.16}],"translate":[{"y":-5.36}]},"Left arm bone top":{"rotate":[{},{"time":0.3,"value":23.7},{"time":0.6667}]},"Right arm bone top":{"rotate":[{},{"time":0.3333,"value":-29.5},{"time":0.6667}]},"Left leg top":{"rotate":[{"value":49.29},{"time":0.2,"value":28.27},{"time":0.4,"value":-11.77},{"time":0.6667,"value":49.29}],"translate":[{"y":-3.98}]},"Right leg bottom":{"rotate":[{"value":-60.43},{"time":0.1,"value":-68.02},{"time":0.2,"value":-12.4},{"time":0.3333,"value":-71.32},{"time":0.4667,"value":-60.51},{"time":0.6667,"value":-60.43}]},"Right leg top":{"rotate":[{"value":49.36},{"time":0.2,"value":-45.45},{"time":0.4,"value":30.44},{"time":0.6667,"value":49.36}],"translate":[{"x":0.29,"y":-4.42}]},"Left leg bottom":{"rotate":[{"value":-55.97},{"time":0.2,"value":-80.82},{"time":0.4,"value":-46.74},{"time":0.6667,"value":-55.97}]}}},"Crouch idle":{"bones":{"Torso bone":{"rotate":[{"value":-6.16}],"translate":[{"y":-5.36},{"time":0.3333,"y":-5.72},{"time":0.6667,"y":-5.36}]},"Left arm bone top":{"rotate":[{},{"time":0.3,"value":0.45},{"time":0.6667}]},"Right arm bone top":{"rotate":[{},{"time":0.3333,"value":-0.86},{"time":0.6667}]},"Left leg top":{"rotate":[{"value":49.29}],"translate":[{"y":-3.98}]},"Right leg bottom":{"rotate":[{"value":-60.43}]},"Right leg top":{"rotate":[{"value":49.36}],"translate":[{"x":0.29,"y":-4.42}]},"Left leg bottom":{"rotate":[{"value":-55.97}]}}},"Idle":{"bones":{"Torso bone":{"translate":[{},{"time":0.1667,"x":0.49,"curve":"stepped"},{"time":1.1667,"x":0.49},{"time":1.3333}]},"Left arm bone top":{"rotate":[{"value":5.19}]},"Right leg top":{"rotate":[{},{"time":0.1667,"value":2.48},{"time":0.3333,"curve":"stepped"},{"time":1.1667},{"time":1.3333,"value":-2.7},{"time":1.5}],"translate":[{},{"time":0.1667,"x":0.49,"curve":"stepped"},{"time":1.1667,"x":0.49},{"time":1.3333}]},"Left leg top":{"rotate":[{},{"time":0.1667,"value":-2.03},{"time":0.3333,"curve":"stepped"},{"time":1.1667},{"time":1.3333,"value":2.53},{"time":1.5}],"translate":[{},{"time":0.1667,"x":0.49,"curve":"stepped"},{"time":1.1667,"x":0.49},{"time":1.3333,"curve":"stepped"},{"time":2.1667}]}}},"Roll":{"bones":{"Torso bone":{"rotate":[{},{"time":0.0667,"value":-88.62},{"time":0.1333,"value":-180.29},{"time":0.2,"value":-270.42},{"time":0.2667,"value":-361.08}],"translate":[{},{"time":0.0667,"x":-0.72,"y":6.21,"curve":"stepped"},{"time":0.1333,"x":-0.72,"y":6.21},{"time":0.2667}]},"Left arm bone top":{"rotate":[{"value":5.19},{"time":0.0667,"value":138.84},{"time":0.1333,"value":5.19}]},"Right arm bone top":{"rotate":[{},{"time":0.0667,"value":129.66},{"time":0.1333}]},"Left leg top":{"rotate":[{},{"time":0.0667,"value":-56.75},{"time":0.1333,"value":-122.94},{"time":0.2,"value":-227.16},{"time":0.2667,"value":-363.15}],"translate":[{},{"time":0.0667,"x":4.48,"y":10.33},{"time":0.1333,"x":9.42,"y":5.02},{"time":0.2,"x":4.01,"y":-2.39},{"time":0.2667}]},"Right leg top":{"rotate":[{},{"time":0.0667,"value":-61.31},{"time":0.1333,"value":-137.71},{"time":0.2,"value":-208.45},{"time":0.2667,"value":-362.4}],"translate":[{},{"time":0.0667,"x":-4.05,"y":1.08},{"time":0.1333,"x":-8.7,"y":4.69},{"time":0.2,"x":-4.52,"y":5.92},{"time":0.2667}]},"Head bone":{"rotate":[{},{"time":0.0667,"value":-47.74},{"time":0.1333,"value":-73.14},{"time":0.2667}]}}},"Run":{"bones":{"Head bone":{"rotate":[{},{"time":0.3333,"value":-6.4},{"time":0.6667}]},"Torso bone":{"rotate":[{"value":-21.66}],"translate":[{"y":-2.21}]},"Left arm bone top":{"rotate":[{},{"time":0.2,"value":48.71},{"time":0.4,"value":-27.24},{"time":0.6667}]},"Right arm bone top":{"rotate":[{},{"time":0.2,"value":-101.29},{"time":0.4,"value":45.1},{"time":0.6667}]},"Left leg top":{"rotate":[{},{"time":0.2,"value":54.81},{"time":0.4,"value":-39.75},{"time":0.6667}],"translate":[{"x":0.61,"y":-0.06}]},"Right leg bottom":{"rotate":[{"value":-39.27},{"time":0.2,"value":-55.63},{"time":0.4,"value":-37.08},{"time":0.6667,"value":-39.27}]},"Right leg top":{"rotate":[{"value":31.8},{"time":0.2,"value":-45.45},{"time":0.4,"value":62.4},{"time":0.6667,"value":31.8}],"translate":[{"y":-2.21}]},"Left leg bottom":{"rotate":[{},{"time":0.1667,"value":-19.82},{"time":0.3333,"value":-3.47},{"time":0.5,"value":-23.09},{"time":0.6667}]},"Left arm bone bottom":{"rotate":[{"value":65.55}]},"Right arm bone bottom":{"rotate":[{"value":82.78}]}}},"Walk":{"bones":{"Head bone":{"rotate":[{},{"time":0.3333,"value":-6.4},{"time":0.6667}]},"Torso bone":{"rotate":[{"value":-6.16}]},"Left arm bone top":{"rotate":[{},{"time":0.3,"value":23.7},{"time":0.6667}]},"Right arm bone top":{"rotate":[{},{"time":0.3333,"value":-29.5},{"time":0.6667}]},"Left leg top":{"rotate":[{},{"time":0.2333,"value":28.27},{"time":0.4333,"value":-11.77},{"time":0.6667}]},"Right leg bottom":{"rotate":[{},{"time":0.1667,"value":-19.82},{"time":0.3,"value":-3.47},{"time":0.4333,"value":-23.09},{"time":0.6667}]},"Right leg top":{"rotate":[{},{"time":0.2333,"value":-45.45},{"time":0.4333,"value":30.44},{"time":0.6667}]},"Left leg bottom":{"rotate":[{},{"time":0.1667,"value":-19.82},{"time":0.3,"value":-3.47},{"time":0.4333,"value":-23.09},{"time":0.6667}]}}}}}